gaspropertycalculator/__init__.py
gaspropertycalculator/dataGui.py
gaspropertycalculator/gaspropertycalculator.py
gaspropertycalculator/generics.py
gaspropertycalculator/parameters.py
gaspropertycalculator/pieChartGui.py
gaspropertycalculator/calculation/__init__.py
gaspropertycalculator/calculation/unitConverter.py
gaspropertycalculator/calculation/util.py
gaspropertycalculator/calculation/eos_gerg/__init__.py
gaspropertycalculator/calculation/eos_gerg/basic.py
gaspropertycalculator/calculation/eos_gerg/calc.py
gaspropertycalculator/calculation/eos_gerg/data.py
gaspropertycalculator/calculation/eos_gerg/util.py
gaspropertycalculator/ui/__init__.py
gaspropertycalculator/ui/resMainWindow_rc.py
gaspropertycalculator/ui/ui_MainWindow.py
gaspropertycalculator-0.0.2.dist-info/LICENSE
gaspropertycalculator-0.0.2.dist-info/METADATA
gaspropertycalculator-0.0.2.dist-info/WHEEL
gaspropertycalculator-0.0.2.dist-info/entry_points.txt
gaspropertycalculator-0.0.2.dist-info/top_level.txt
gaspropertycalculator-0.0.2.dist-info/RECORD
