Metadata-Version: 2.1
Name: gaspropertycalculator
Version: 0.0.2
Summary: GasPropertyCalculator
Home-page: UNKNOWN
Author: Michael Fischer
Author-email: mfischer.sw@gmail.com
License: UNKNOWN
Project-URL: Source, https://github.com/mfischersw/GasPropertyCalculator/
Platform: UNKNOWN
Requires-Python: >=3.7, <4
License-File: LICENSE
